analyze_the_shit_outof_me/__init__.py
analyze_the_shit_outof_me/twitter_analysis.py
analyze_the_shit_out_of_me-0.0.5.dist-info/METADATA
analyze_the_shit_out_of_me-0.0.5.dist-info/WHEEL
analyze_the_shit_out_of_me-0.0.5.dist-info/top_level.txt
analyze_the_shit_out_of_me-0.0.5.dist-info/RECORD
