Metadata-Version: 2.1
Name: analyze_the_shit_out_of_me
Version: 0.0.5
Summary: Twitter Sentiment Analysis package
Home-page: UNKNOWN
Author: Mirzabek Matyakubov
Author-email: <markmatyakubov@gmail.com
License: UNKNOWN
Keywords: python,simpleCalpackage
Platform: UNKNOWN
Classifier: Development Status :: 3 - Alpha
Classifier: Intended Audience :: Education
Classifier: Programming Language :: Python :: 2
Classifier: Programming Language :: Python :: 3
Classifier: Operating System :: MacOS :: MacOS X
Classifier: Operating System :: Microsoft :: Windows
